haystack_unstructured_fileconverter/__about__.py
haystack_unstructured_fileconverter/__init__.py
haystack_unstructured_fileconverter/fileconverter.py
haystack_unstructured_fileconverter-0.0.2.dist-info/METADATA
haystack_unstructured_fileconverter-0.0.2.dist-info/WHEEL
haystack_unstructured_fileconverter-0.0.2.dist-info/RECORD
