Metadata-Version: 2.1
Name: haystack-unstructured-fileconverter
Version: 0.0.2
Summary: Haystack 2.x component to convert files into Documents using the Unstructured API
Project-URL: Documentation, https://github.com/anakin87/haystack-unstructured-fileconverter#readme
Project-URL: Issues, https://github.com/anakin87/haystack-unstructured-fileconverter/issues
Project-URL: Source, https://github.com/anakin87/haystack-unstructured-fileconverter
Author-email: anakin87 <stefanofiorucci@gmail.com>
License-Expression: Apache-2.0
Classifier: Development Status :: 4 - Beta
Classifier: Programming Language :: Python
Classifier: Programming Language :: Python :: 3.8
Classifier: Programming Language :: Python :: 3.9
Classifier: Programming Language :: Python :: 3.10
Classifier: Programming Language :: Python :: 3.11
Classifier: Programming Language :: Python :: Implementation :: CPython
Classifier: Programming Language :: Python :: Implementation :: PyPy
Requires-Python: >=3.8
Requires-Dist: haystack-ai
Requires-Dist: unstructured
